xml_serializer/__init__.py
xml_serializer/abstract_type.py
xml_serializer/converter_types.py
xml_serializer/main.py
xml_serializer/schema_items.py
xml_serializer-1.0.5.dist-info/LICENSE
xml_serializer-1.0.5.dist-info/METADATA
xml_serializer-1.0.5.dist-info/WHEEL
xml_serializer-1.0.5.dist-info/top_level.txt
xml_serializer-1.0.5.dist-info/RECORD
