Metadata-Version: 2.1
Name: xml_serializer
Version: 1.0.5
Summary: Module for serialize (convert) xml to Python dict (with Python objects)
Home-page: https://github.com/Eff1c/xml_serializer
Author: Illia Martyniuk
Author-email: illymartynyk@gmail.com
License: MIT
Classifier: Programming Language :: Python :: 3
Classifier: License :: OSI Approved :: MIT License
Classifier: Operating System :: OS Independent
Requires-Python: >=3.6
License-File: LICENSE
